odoo/addons/product_supplierinfo_standard_price/README.rst
odoo/addons/product_supplierinfo_standard_price/__init__.py
odoo/addons/product_supplierinfo_standard_price/__manifest__.py
odoo/addons/product_supplierinfo_standard_price/i18n/fr.po
odoo/addons/product_supplierinfo_standard_price/i18n/it.po
odoo/addons/product_supplierinfo_standard_price/i18n/product_supplierinfo_standard_price.pot
odoo/addons/product_supplierinfo_standard_price/models/__init__.py
odoo/addons/product_supplierinfo_standard_price/models/product_supplierinfo.py
odoo/addons/product_supplierinfo_standard_price/readme/CONTRIBUTORS.rst
odoo/addons/product_supplierinfo_standard_price/readme/DESCRIPTION.rst
odoo/addons/product_supplierinfo_standard_price/static/description/changing_standardprice_from_supplierinfo.jpeg
odoo/addons/product_supplierinfo_standard_price/static/description/icon.png
odoo/addons/product_supplierinfo_standard_price/static/description/index.html
odoo/addons/product_supplierinfo_standard_price/static/src/scss/product_supplierinfo_standard_price.scss
odoo/addons/product_supplierinfo_standard_price/tests/__init__.py
odoo/addons/product_supplierinfo_standard_price/tests/test_standard_price.py
odoo/addons/product_supplierinfo_standard_price/views/view_product_supplierinfo.xml
odoo_addon_product_supplierinfo_standard_price-16.0.1.0.0.7.dist-info/METADATA
odoo_addon_product_supplierinfo_standard_price-16.0.1.0.0.7.dist-info/WHEEL
odoo_addon_product_supplierinfo_standard_price-16.0.1.0.0.7.dist-info/top_level.txt
odoo_addon_product_supplierinfo_standard_price-16.0.1.0.0.7.dist-info/RECORD
