Metadata-Version: 2.1
Name: odoo-addon-product_supplierinfo_standard_price
Version: 16.0.1.0.0.7
Summary: Product supplier easily connected to product's standard price
Home-page: https://github.com/OCA/product-attribute
Author: GRAP, Odoo Community Association (OCA)
Author-email: support@odoo-community.org
License: AGPL-3
Classifier: Programming Language :: Python
Classifier: Framework :: Odoo
Classifier: Framework :: Odoo :: 16.0
Classifier: License :: OSI Approved :: GNU Affero General Public License v3
Requires-Python: >=3.10
Requires-Dist: odoo-addon-web-notify<16.1dev,>=16.0dev
Requires-Dist: odoo<16.1dev,>=16.0a
